rake_ja/__init__.py
rake_ja/rake_ja.py
rake_ja/tokenizer.py
rake_ja-0.0.1.dist-info/LICENSE
rake_ja-0.0.1.dist-info/METADATA
rake_ja-0.0.1.dist-info/WHEEL
rake_ja-0.0.1.dist-info/top_level.txt
rake_ja-0.0.1.dist-info/RECORD
